plmdp/__init__.py
plmdp/constants.py
plmdp/enums.py
plmdp/exceptions.py
plmdp/metrics_handler_factory.py
plmdp/primitives.py
plmdp/profiler.py
plmdp/cli/__init__.py
plmdp/cli/cli.py
plmdp/cli/data_loader.py
plmdp/cli/formatter.py
plmdp/cli/input_utils.py
plmdp/models/__init__.py
plmdp/models/_string.py
plmdp/models/date_or_datetime.py
plmdp/models/numeric.py
plmdp/models/output.py
plmdp/models/type_agnostic.py
plmdp/service/__init__.py
plmdp/service/_string.py
plmdp/service/date_or_datetime.py
plmdp/service/numeric.py
plmdp/service/type_agnostic.py
plmdp-0.1.5.dist-info/METADATA
plmdp-0.1.5.dist-info/WHEEL
plmdp-0.1.5.dist-info/entry_points.txt
plmdp-0.1.5.dist-info/top_level.txt
plmdp-0.1.5.dist-info/RECORD
