Metadata-Version: 2.2
Name: plmdp
Version: 0.1.5
Summary: Polars minimal data profiler.
Project-URL: Repository, https://github.com/ddymkowski/mdp
Requires-Python: >=3.12
Requires-Dist: polars>=1.22.0
Requires-Dist: pyyaml>=6.0.2
